<?xml version='1.0' encoding='utf-8'?>
<dashboard refresh="600">
  <!--
NOTE: This file was automatically generated by Splunk.  Use caution when editing manually.
-->
  <label>SymbolErrors (24 hour window)</label>
  <row>
    <chart>
      <searchName>IB: SymbolErrors (Active, Host, 24hr)</searchName>
      <title>Currently Active ports (SymbolErrors running sum)</title>
      <option name="drilldown">all</option>
    </chart>
    <chart>
      <searchName>Infiniband: route changes plot</searchName>
      <title>Number of routing path changes (30min bins)</title>
      <option name="drilldown">all</option>
    </chart>
  </row>
  <row>
    <table>
      <searchName>Infiniband: SymbolErrors on all ports (24hr sum per state)</searchName>
      <title>All ports (SymbolErrors sum per state,hostport)</title>
      <option name="drilldown">row</option>
    </table>
    <table>
      <searchName>Infiniband: SymbolErrors hostport vs state ctable</searchName>
      <title>Number of SymbolErrors&gt;0 samples per hostport,state</title>
      <option name="drilldown">row</option>
    </table>
  </row>
</dashboard>
